opencellid/__init__.py
opencellid/opencellid_feed.py
opencellid-1.2.dist-info/DESCRIPTION.rst
opencellid-1.2.dist-info/METADATA
opencellid-1.2.dist-info/RECORD
opencellid-1.2.dist-info/WHEEL
opencellid-1.2.dist-info/metadata.json
opencellid-1.2.dist-info/top_level.txt
