Metadata-Version: 2.0
Name: opencellid
Version: 1.2
Summary: A python wrapper for the OpenCellID DB
Home-page: https://github.com/ashmastaflash/opencellid-wrapper
Author: Ash Wilson
Author-email: ash.d.wilson@gmail.com
License: BSD
Keywords: opencellid
Platform: UNKNOWN
Classifier: Programming Language :: Python :: 2.7
Requires-Dist: requests
